django_mailgun/__init__.py
django_mailgun_redux-0.3.0.dist-info/DESCRIPTION.rst
django_mailgun_redux-0.3.0.dist-info/METADATA
django_mailgun_redux-0.3.0.dist-info/metadata.json
django_mailgun_redux-0.3.0.dist-info/RECORD
django_mailgun_redux-0.3.0.dist-info/top_level.txt
django_mailgun_redux-0.3.0.dist-info/WHEEL
