Metadata-Version: 2.0
Name: django-mailgun-redux
Version: 0.3.0
Summary: A Django email backend for Mailgun
Home-page: http://github.com/pydanny/django-mailgun/
Author: Bradley Whittington, Daniel Roy Greenfeld
Author-email: pydanny@gmail.com
License: MIT
Platform: any
Classifier: Development Status :: 4 - Beta
Classifier: Intended Audience :: Developers
Classifier: License :: OSI Approved :: MIT License
Classifier: Operating System :: OS Independent
Classifier: Programming Language :: Python
Classifier: Topic :: Software Development :: Libraries :: Python Modules
Classifier: Framework :: Django
Requires-Dist: requests
